pydbc/__init__.py
pydbc/api/dbc/__init__.py
pydbc/api/ldf/__init__.py
pydbc/api/ncf/__init__.py
pydbc/asam/__init__.py
pydbc/asam/types.py
pydbc/buildGrammars.cmd
pydbc/buildGrammars.sh
pydbc/cgen/__init__.py
pydbc/cgen/generators.py
pydbc/cgen/templates/__init__.py
pydbc/cgen/templates/dbc.tmpl
pydbc/cgen/templates/ldf.tmpl
pydbc/cgen/templates/micropython_can.py.tmpl
pydbc/cgen/templates/socketcan.c.tmpl
pydbc/db/__init__.py
pydbc/db/imex.py
pydbc/db/model.py
pydbc/dbc.g4
pydbc/dbcListener.py
pydbc/examples/api_examples.py
pydbc/examples/create_candb.py
pydbc/exceptions.py
pydbc/integrations/__init__.py
pydbc/integrations/python_can.py
pydbc/ldf.g4
pydbc/ldfListener.py
pydbc/logger.py
pydbc/ncf.g4
pydbc/ncfListener.py
pydbc/parser.py
pydbc/py3/__init__.py
pydbc/py3/dbc.tokens
pydbc/py3/dbcLexer.py
pydbc/py3/dbcLexer.tokens
pydbc/py3/dbcListener.py
pydbc/py3/dbcParser.py
pydbc/py3/dbcVisitor.py
pydbc/py3/ldf.tokens
pydbc/py3/ldfLexer.py
pydbc/py3/ldfLexer.tokens
pydbc/py3/ldfParser.py
pydbc/py3/ldfVisitor.py
pydbc/py3/ncf.tokens
pydbc/py3/ncfLexer.py
pydbc/py3/ncfLexer.tokens
pydbc/py3/ncfParser.py
pydbc/py3/ncfVisitor.py
pydbc/scripts/__init__.py
pydbc/scripts/vndb_exporter.py
pydbc/scripts/vndb_importer.py
pydbc/template.py
pydbc/tests/__init__.py
pydbc/tests/base.py
pydbc/tests/test_dbc_parser.py
pydbc/tests/test_types.py
pydbc/types.py
pydbc/utils.py
pydbc/version.py
pyvndb-1.0.115.dist-info/METADATA
pyvndb-1.0.115.dist-info/WHEEL
pyvndb-1.0.115.dist-info/entry_points.txt
pyvndb-1.0.115.dist-info/licenses/LICENSE
pyvndb-1.0.115.dist-info/RECORD
