Metadata-Version: 2.4
Name: pyvndb
Version: 1.0.115
Summary: Vehicle description file handling for Python
License: GPL-2.0-only
License-File: LICENSE
Author: Christoph Schueler
Author-email: cpu12.gems@googlemail.com
Requires-Python: >=3.10
Classifier: Development Status :: 4 - Beta
Classifier: Intended Audience :: Developers
Classifier: License :: OSI Approved :: GNU General Public License v2 (GPLv2)
Classifier: Programming Language :: Python :: 3
Classifier: Programming Language :: Python :: 3.10
Classifier: Programming Language :: Python :: 3.11
Classifier: Programming Language :: Python :: 3.12
Classifier: Programming Language :: Python :: 3.13
Classifier: Programming Language :: Python :: 3.14
Classifier: Topic :: Scientific/Engineering
Classifier: Topic :: Software Development
Provides-Extra: python-can
Requires-Dist: SQLAlchemy (>=2.0.0)
Requires-Dist: antlr4-python3-runtime (==4.13.2)
Requires-Dist: chardet (>=5.0.0)
Requires-Dist: colorama (>=0.4.6)
Requires-Dist: mako (>=1.2.0)
Requires-Dist: python-can ; extra == "python-can"
Requires-Dist: typing-extensions (>=4.0.0)
Project-URL: Repository, https://www.github.com/Christoph2/pydbc
